{
  "active_list": "adi_tpot",
  "lists": {
    "og_tpot": [
      "prerationalist",
      "the_wilderless",
      "nosilverv",
      "vividvoid_",
      "goblinodds",
      "eigenrobot",
      "exgenesis",
      "becomingcritter",
      "malcolm_ocean",
      "m_ashcroft",
      "visakanv",
      "tasshinfogleman"
    ]
  },
  "settings": {
    "alpha": 0.85,
    "auto_include_shadow": true,
    "discovery_weights": {
      "community": 0.20000000000000004,
      "neighbor_overlap": 0.4000000000000001,
      "pagerank": 0.30000000000000004,
      "path_distance": 0.10000000000000002
    },
    "hierarchy_engine": "v1",
    "limit": 500,
    "max_distance": 3,
    "membership_engine": "off",
    "obs_completeness_floor": 0.01,
    "obs_p_min": 0.01,
    "obs_weighting": "off"
  },
  "updated_at": "2025-12-07T04:03:57.609954+00:00"
}
